uipath_connectors/google_drive/__init__.py
uipath_connectors/google_drive/client.py
uipath_connectors/google_drive/errors.py
uipath_connectors/google_drive/py.typed
uipath_connectors/google_drive/types.py
uipath_connectors/google_drive/api/__init__.py
uipath_connectors/google_drive/api/copy_file/__init__.py
uipath_connectors/google_drive/api/copy_file/copy_file.py
uipath_connectors/google_drive/api/create_folder/__init__.py
uipath_connectors/google_drive/api/create_folder/create_folder.py
uipath_connectors/google_drive/api/delete_fileor_folder/__init__.py
uipath_connectors/google_drive/api/delete_fileor_folder/delete_fileor_folder.py
uipath_connectors/google_drive/api/download_file/__init__.py
uipath_connectors/google_drive/api/download_file/download_file.py
uipath_connectors/google_drive/api/get_file_labels/__init__.py
uipath_connectors/google_drive/api/get_file_labels/get_file_labels.py
uipath_connectors/google_drive/api/get_fileor_folder/__init__.py
uipath_connectors/google_drive/api/get_fileor_folder/get_file_or_folder.py
uipath_connectors/google_drive/api/get_fileor_folder_list/__init__.py
uipath_connectors/google_drive/api/get_fileor_folder_list/get_fileor_folder_list.py
uipath_connectors/google_drive/api/labels/__init__.py
uipath_connectors/google_drive/api/labels/get_drive_labels.py
uipath_connectors/google_drive/api/modify_label/__init__.py
uipath_connectors/google_drive/api/modify_label/apply_labels.py
uipath_connectors/google_drive/api/move_fileor_folder/__init__.py
uipath_connectors/google_drive/api/move_fileor_folder/move_fileor_folder.py
uipath_connectors/google_drive/api/remove_labels/__init__.py
uipath_connectors/google_drive/api/remove_labels/remove_labels.py
uipath_connectors/google_drive/api/share_file_or_folder/__init__.py
uipath_connectors/google_drive/api/share_file_or_folder/share_file_or_folder.py
uipath_connectors/google_drive/api/upload_file/__init__.py
uipath_connectors/google_drive/api/upload_file/upload_files.py
uipath_connectors_google_drive-1.11.0.dev12.dist-info/METADATA
uipath_connectors_google_drive-1.11.0.dev12.dist-info/WHEEL
uipath_connectors_google_drive-1.11.0.dev12.dist-info/entry_points.txt
uipath_connectors_google_drive-1.11.0.dev12.dist-info/top_level.txt
uipath_connectors_google_drive-1.11.0.dev12.dist-info/RECORD
